olympyc/__init__.py
olympyc/ms_s3.py
olympyc/s3io.py
olympyc/s3io_old.py
olympyc-0.0.1.dist-info/LICENSE
olympyc-0.0.1.dist-info/METADATA
olympyc-0.0.1.dist-info/WHEEL
olympyc-0.0.1.dist-info/top_level.txt
olympyc-0.0.1.dist-info/RECORD
