Metadata-Version: 2.1
Name: olympyc
Version: 0.0.1
Summary: s3 io stuff
Home-page: https://github.com/thorwhalen/ut/tree/master/olympyc
Author: Thor Whalen
License: mit
Platform: any
